[
 {
  "System": "http://snomed.info/sct",
  "Version": "2021-03",
  "Code": "10596002",
  "Display": "Peripheral vascular complication (disorder)"
 },
 {
  "System": "http://snomed.info/sct",
  "Version": "2021-03",
  "Code": "27550009",
  "Display": "Disorder of blood vessel (disorder)"
 },
 {
  "System": "http://snomed.info/sct",
  "Version": "2021-03",
  "Code": "400047006",
  "Display": "Peripheral vascular disease (disorder)"
 },
 {
  "System": "http://snomed.info/sct",
  "Version": "2021-03",
  "Code": "473109007",
  "Display": "History of peripheral vascular disease (situation)"
 },
 {
  "System": "http://snomed.info/sct",
  "Version": "2021-03",
  "Code": "473449006",
  "Display": "Disease of non-coronary systemic artery (disorder)"
 },
 {
  "System": "http://hl7.org/fhir/sid/icd-10-cm",
  "Version": "2022",
  "Code": "I73.89",
  "Display": "Other specified peripheral vascular diseases"
 },
 {
  "System": "http://hl7.org/fhir/sid/icd-10-cm",
  "Version": "2022",
  "Code": "I73.9",
  "Display": "Peripheral vascular disease"
 }
]