[
 {
  "System": "http://snomed.info/sct",
  "Version": "2021-03",
  "Code": "10528009",
  "Display": "Lupus vulgaris (disorder)"
 },
 {
  "System": "http://snomed.info/sct",
  "Version": "2021-03",
  "Code": "10706006",
  "Display": "Tuberculosis of central nervous system (disorder)"
 },
 {
  "System": "http://snomed.info/sct",
  "Version": "2021-03",
  "Code": "10759881000119100",
  "Display": "Tuberculosis in mother complicating childbirth (disorder)"
 },
 {
  "System": "http://snomed.info/sct",
  "Version": "2021-03",
  "Code": "10893003",
  "Display": "Tuberculous adenitis (disorder)"
 },
 {
  "System": "http://snomed.info/sct",
  "Version": "2021-03",
  "Code": "1092771000119104",
  "Display": "Tuberculous neuritis (disorder)"
 },
 {
  "System": "http://snomed.info/sct",
  "Version": "2021-03",
  "Code": "111825008",
  "Display": "Tuberculosis of conjunctiva (disorder)"
 },
 {
  "System": "http://snomed.info/sct",
  "Version": "2021-03",
  "Code": "111830007",
  "Display": "Tuberculosis of urinary organs (disorder)"
 },
 {
  "System": "http://snomed.info/sct",
  "Version": "2021-03",
  "Code": "111832004",
  "Display": "Primary progressive tuberculosis (disorder)"
 },
 {
  "System": "http://snomed.info/sct",
  "Version": "2021-03",
  "Code": "11676005",
  "Display": "Tuberculous leptomeningitis (disorder)"
 },
 {
  "System": "http://snomed.info/sct",
  "Version": "2021-03",
  "Code": "11999007",
  "Display": "Inactive tuberculosis (disorder)"
 },
 {
  "System": "http://snomed.info/sct",
  "Version": "2021-03",
  "Code": "12137005",
  "Display": "Tuberculous enteritis (disorder)"
 },
 {
  "System": "http://snomed.info/sct",
  "Version": "2021-03",
  "Code": "12677003",
  "Display": "Tuberculosis of brain (disorder)"
 },
 {
  "System": "http://snomed.info/sct",
  "Version": "2021-03",
  "Code": "129211000119108",
  "Display": "Isoniazid resistant tuberculosis of lung (disorder)"
 },
 {
  "System": "http://snomed.info/sct",
  "Version": "2021-03",
  "Code": "12985005",
  "Display": "Tuberculosis of seminal vesicle (disorder)"
 },
 {
  "System": "http://snomed.info/sct",
  "Version": "2021-03",
  "Code": "13570003",
  "Display": "Tuberculous tenosynovitis (disorder)"
 },
 {
  "System": "http://snomed.info/sct",
  "Version": "2021-03",
  "Code": "14188007",
  "Display": "Tuberculosis of hip (disorder)"
 },
 {
  "System": "http://snomed.info/sct",
  "Version": "2021-03",
  "Code": "14527007",
  "Display": "Tuberculous empyema (disorder)"
 },
 {
  "System": "http://snomed.info/sct",
  "Version": "2021-03",
  "Code": "15202009",
  "Display": "Tuberculoma (disorder)"
 },
 {
  "System": "http://snomed.info/sct",
  "Version": "2021-03",
  "Code": "15284007",
  "Display": "Tuberculosis of esophagus (disorder)"
 },
 {
  "System": "http://snomed.info/sct",
  "Version": "2021-03",
  "Code": "154283005",
  "Display": "Pulmonary tuberculosis (disorder)"
 },
 {
  "System": "http://snomed.info/sct",
  "Version": "2021-03",
  "Code": "16016231000119109",
  "Display": "Tuberculosis of right knee joint (disorder)"
 },
 {
  "System": "http://snomed.info/sct",
  "Version": "2021-03",
  "Code": "16016311000119107",
  "Display": "Tuberculosis of left knee joint (disorder)"
 },
 {
  "System": "http://snomed.info/sct",
  "Version": "2021-03",
  "Code": "161414005",
  "Display": "History of tuberculosis (situation)"
 },
 {
  "System": "http://snomed.info/sct",
  "Version": "2021-03",
  "Code": "16409009",
  "Display": "Tuberculosis of retroperitoneal lymph nodes (disorder)"
 },
 {
  "System": "http://snomed.info/sct",
  "Version": "2021-03",
  "Code": "17136009",
  "Display": "Tuberculosis of knee (disorder)"
 },
 {
  "System": "http://snomed.info/sct",
  "Version": "2021-03",
  "Code": "17653001",
  "Display": "Tuberculosis of bones and/or joints (disorder)"
 },
 {
  "System": "http://snomed.info/sct",
  "Version": "2021-03",
  "Code": "182159002",
  "Display": "Disseminated tuberculosis (disorder)"
 },
 {
  "System": "http://snomed.info/sct",
  "Version": "2021-03",
  "Code": "185113005",
  "Display": "Tuberculosis of adrenal glands (disorder)"
 },
 {
  "System": "http://snomed.info/sct",
  "Version": "2021-03",
  "Code": "186172004",
  "Display": "Tuberculous pleurisy in primary progressive tuberculosis (disorder)"
 },
 {
  "System": "http://snomed.info/sct",
  "Version": "2021-03",
  "Code": "186175002",
  "Display": "Infiltrative lung tuberculosis (disorder)"
 },
 {
  "System": "http://snomed.info/sct",
  "Version": "2021-03",
  "Code": "186177005",
  "Display": "Tuberculosis of lung with cavitation (disorder)"
 },
 {
  "System": "http://snomed.info/sct",
  "Version": "2021-03",
  "Code": "186178000",
  "Display": "Tuberculosis of bronchus (disorder)"
 },
 {
  "System": "http://snomed.info/sct",
  "Version": "2021-03",
  "Code": "186182003",
  "Display": "Tuberculosis of pleura (disorder)"
 },
 {
  "System": "http://snomed.info/sct",
  "Version": "2021-03",
  "Code": "186192006",
  "Display": "Respiratory tuberculosis"
 },
 {
  "System": "http://snomed.info/sct",
  "Version": "2021-03",
  "Code": "186193001",
  "Display": "Tuberculosis of lung"
 },
 {
  "System": "http://snomed.info/sct",
  "Version": "2021-03",
  "Code": "186194007",
  "Display": "Tuberculosis of lung"
 },
 {
  "System": "http://snomed.info/sct",
  "Version": "2021-03",
  "Code": "186195008",
  "Display": "Tuberculosis of lung"
 },
 {
  "System": "http://snomed.info/sct",
  "Version": "2021-03",
  "Code": "186199002",
  "Display": "Tuberculosis of larynx"
 },
 {
  "System": "http://snomed.info/sct",
  "Version": "2021-03",
  "Code": "186200004",
  "Display": "Tuberculous pleurisy"
 },
 {
  "System": "http://snomed.info/sct",
  "Version": "2021-03",
  "Code": "186201000",
  "Display": "Primary respiratory tuberculosis"
 },
 {
  "System": "http://snomed.info/sct",
  "Version": "2021-03",
  "Code": "186202007",
  "Display": "Respiratory tuberculosis"
 },
 {
  "System": "http://snomed.info/sct",
  "Version": "2021-03",
  "Code": "186203002",
  "Display": "Tuberculosis of lung"
 },
 {
  "System": "http://snomed.info/sct",
  "Version": "2021-03",
  "Code": "186204008",
  "Display": "Tuberculosis of lung"
 },
 {
  "System": "http://snomed.info/sct",
  "Version": "2021-03",
  "Code": "186225008",
  "Display": "Tuberculosis of intestines"
 },
 {
  "System": "http://snomed.info/sct",
  "Version": "2021-03",
  "Code": "186259007",
  "Display": "Scrofulous tuberculous abscess (disorder)"
 },
 {
  "System": "http://snomed.info/sct",
  "Version": "2021-03",
  "Code": "186263000",
  "Display": "Tuberculous chorioretinitis (disorder)"
 },
 {
  "System": "http://snomed.info/sct",
  "Version": "2021-03",
  "Code": "186266008",
  "Display": "Tuberculous chronic iridocyclitis (disorder)"
 },
 {
  "System": "http://snomed.info/sct",
  "Version": "2021-03",
  "Code": "186267004",
  "Display": "Tuberculous keratoconjunctivitis (disorder)"
 },
 {
  "System": "http://snomed.info/sct",
  "Version": "2021-03",
  "Code": "186269001",
  "Display": "Tuberculosis of ear (disorder)"
 },
 {
  "System": "http://snomed.info/sct",
  "Version": "2021-03",
  "Code": "186270000",
  "Display": "Tuberculous Addison's disease (disorder)"
 },
 {
  "System": "http://snomed.info/sct",
  "Version": "2021-03",
  "Code": "186272008",
  "Display": "Tuberculosis of stomach (disorder)"
 },
 {
  "System": "http://snomed.info/sct",
  "Version": "2021-03",
  "Code": "186273003",
  "Display": "Tuberculosis of liver (disorder)"
 },
 {
  "System": "http://snomed.info/sct",
  "Version": "2021-03",
  "Code": "186276006",
  "Display": "Acute miliary tuberculosis (disorder)"
 },
 {
  "System": "http://snomed.info/sct",
  "Version": "2021-03",
  "Code": "186278007",
  "Display": "Acute miliary tuberculosis of multiple sites (disorder)"
 },
 {
  "System": "http://snomed.info/sct",
  "Version": "2021-03",
  "Code": "190710003",
  "Display": "Tuberculous arthritis (disorder)"
 },
 {
  "System": "http://snomed.info/sct",
  "Version": "2021-03",
  "Code": "193787009",
  "Display": "Keratitis caused by tuberculosis (disorder)"
 },
 {
  "System": "http://snomed.info/sct",
  "Version": "2021-03",
  "Code": "194908003",
  "Display": "Acute tuberculous pericarditis (disorder)"
 },
 {
  "System": "http://snomed.info/sct",
  "Version": "2021-03",
  "Code": "194949003",
  "Display": "Acute myocarditis - tuberculous (disorder)"
 },
 {
  "System": "http://snomed.info/sct",
  "Version": "2021-03",
  "Code": "198241002",
  "Display": "Female tuberculous pelvic inflammatory disease (disorder)"
 },
 {
  "System": "http://snomed.info/sct",
  "Version": "2021-03",
  "Code": "199175001",
  "Display": "Maternal tuberculosis during pregnancy"
 },
 {
  "System": "http://snomed.info/sct",
  "Version": "2021-03",
  "Code": "199178004",
  "Display": "Tuberculosis in pregnancy"
 },
 {
  "System": "http://snomed.info/sct",
  "Version": "2021-03",
  "Code": "199179007",
  "Display": "Maternal tuberculosis in the puerperium - baby delivered during current episode of care (disorder)"
 },
 {
  "System": "http://snomed.info/sct",
  "Version": "2021-03",
  "Code": "199180005",
  "Display": "Maternal tuberculosis during pregnancy - baby not yet delivered (disorder)"
 },
 {
  "System": "http://snomed.info/sct",
  "Version": "2021-03",
  "Code": "199181009",
  "Display": "Maternal tuberculosis in the puerperium - baby delivered during previous episode of care (disorder)"
 },
 {
  "System": "http://snomed.info/sct",
  "Version": "2021-03",
  "Code": "202994006",
  "Display": "Tuberculous infection of tendon sheath (disorder)"
 },
 {
  "System": "http://snomed.info/sct",
  "Version": "2021-03",
  "Code": "203263006",
  "Display": "Tuberculosis of cervical spine (disorder)"
 },
 {
  "System": "http://snomed.info/sct",
  "Version": "2021-03",
  "Code": "203264000",
  "Display": "Tuberculosis of thoracic spine (disorder)"
 },
 {
  "System": "http://snomed.info/sct",
  "Version": "2021-03",
  "Code": "203265004",
  "Display": "Tuberculosis of lumbar spine (disorder)"
 },
 {
  "System": "http://snomed.info/sct",
  "Version": "2021-03",
  "Code": "203267007",
  "Display": "Tuberculosis of limb bones (disorder)"
 },
 {
  "System": "http://snomed.info/sct",
  "Version": "2021-03",
  "Code": "203269005",
  "Display": "Tuberculosis of the upper arm bone (disorder)"
 },
 {
  "System": "http://snomed.info/sct",
  "Version": "2021-03",
  "Code": "203270006",
  "Display": "Tuberculosis of the forearm bone (disorder)"
 },
 {
  "System": "http://snomed.info/sct",
  "Version": "2021-03",
  "Code": "203271005",
  "Display": "Tuberculosis of the pelvic and/or thigh bones (disorder)"
 },
 {
  "System": "http://snomed.info/sct",
  "Version": "2021-03",
  "Code": "203272003",
  "Display": "Tuberculosis of the lower leg bone (disorder)"
 },
 {
  "System": "http://snomed.info/sct",
  "Version": "2021-03",
  "Code": "203274002",
  "Display": "Tuberculosis of multiple limb bones (disorder)"
 },
 {
  "System": "http://snomed.info/sct",
  "Version": "2021-03",
  "Code": "203278004",
  "Display": "Tuberculosis of the bones of the shoulder region (disorder)"
 },
 {
  "System": "http://snomed.info/sct",
  "Version": "2021-03",
  "Code": "203279007",
  "Display": "Tuberculosis of the bones of the hand (disorder)"
 },
 {
  "System": "http://snomed.info/sct",
  "Version": "2021-03",
  "Code": "203280005",
  "Display": "Tuberculosis of the bones of the ankle and/or foot (disorder)"
 },
 {
  "System": "http://snomed.info/sct",
  "Version": "2021-03",
  "Code": "203282002",
  "Display": "Tuberculosis of the bones of multiple sites (disorder)"
 },
 {
  "System": "http://snomed.info/sct",
  "Version": "2021-03",
  "Code": "20372007",
  "Display": "Tuberculosis of prostate (disorder)"
 },
 {
  "System": "http://snomed.info/sct",
  "Version": "2021-03",
  "Code": "213580002",
  "Display": "Caseating tuberculoid granuloma (disorder)"
 },
 {
  "System": "http://snomed.info/sct",
  "Version": "2021-03",
  "Code": "22990009",
  "Display": "Chronic tuberculosis (disorder)"
 },
 {
  "System": "http://snomed.info/sct",
  "Version": "2021-03",
  "Code": "233649005",
  "Display": "Tuberculous chylothorax (disorder)"
 },
 {
  "System": "http://snomed.info/sct",
  "Version": "2021-03",
  "Code": "233763009",
  "Display": "Silicotuberculosis (disorder)"
 },
 {
  "System": "http://snomed.info/sct",
  "Version": "2021-03",
  "Code": "233794009",
  "Display": "Tuberculous bronchopleural fistula (disorder)"
 },
 {
  "System": "http://snomed.info/sct",
  "Version": "2021-03",
  "Code": "234090004",
  "Display": "Tuberculous mesenteric adenitis (disorder)"
 },
 {
  "System": "http://snomed.info/sct",
  "Version": "2021-03",
  "Code": "235067001",
  "Display": "Oral tuberculosis (disorder)"
 },
 {
  "System": "http://snomed.info/sct",
  "Version": "2021-03",
  "Code": "235694001",
  "Display": "Tuberculous duodenitis (disorder)"
 },
 {
  "System": "http://snomed.info/sct",
  "Version": "2021-03",
  "Code": "236602004",
  "Display": "Tuberculous stricture of ureter (disorder)"
 },
 {
  "System": "http://snomed.info/sct",
  "Version": "2021-03",
  "Code": "236684001",
  "Display": "Tuberculous urethritis (disorder)"
 },
 {
  "System": "http://snomed.info/sct",
  "Version": "2021-03",
  "Code": "236770001",
  "Display": "Tuberculous epididymo-orchitis (disorder)"
 },
 {
  "System": "http://snomed.info/sct",
  "Version": "2021-03",
  "Code": "237445009",
  "Display": "Tuberculosis of breast (disorder)"
 },
 {
  "System": "http://snomed.info/sct",
  "Version": "2021-03",
  "Code": "238430004",
  "Display": "Cutaneous complication of bacillus Calmette-Guerin immunization (disorder)"
 },
 {
  "System": "http://snomed.info/sct",
  "Version": "2021-03",
  "Code": "238431000",
  "Display": "Bacillus Calmette-Guerin granuloma (disorder)"
 },
 {
  "System": "http://snomed.info/sct",
  "Version": "2021-03",
  "Code": "238432007",
  "Display": "Bacillus Calmette-Guerin ulcer (disorder)"
 },
 {
  "System": "http://snomed.info/sct",
  "Version": "2021-03",
  "Code": "240376003",
  "Display": "Tuberculosis of gastrointestinal tract (disorder)"
 },
 {
  "System": "http://snomed.info/sct",
  "Version": "2021-03",
  "Code": "240379005",
  "Display": "Tuberculosis of male genital organs (disorder)"
 },
 {
  "System": "http://snomed.info/sct",
  "Version": "2021-03",
  "Code": "240380008",
  "Display": "Acute tuberculous ulcer (disorder)"
 },
 {
  "System": "http://snomed.info/sct",
  "Version": "2021-03",
  "Code": "240381007",
  "Display": "Acute miliary cutaneous tuberculosis (disorder)"
 },
 {
  "System": "http://snomed.info/sct",
  "Version": "2021-03",
  "Code": "240382000",
  "Display": "Cutaneous tuberculous gumma (disorder)"
 },
 {
  "System": "http://snomed.info/sct",
  "Version": "2021-03",
  "Code": "24235005",
  "Display": "Tuberculous hydrothorax (disorder)"
 },
 {
  "System": "http://snomed.info/sct",
  "Version": "2021-03",
  "Code": "24810006",
  "Display": "Tuberculosis orificialis of mouth (disorder)"
 },
 {
  "System": "http://snomed.info/sct",
  "Version": "2021-03",
  "Code": "25629007",
  "Display": "Acute tuberculosis (disorder)"
 },
 {
  "System": "http://snomed.info/sct",
  "Version": "2021-03",
  "Code": "25738004",
  "Display": "Tuberculous synovitis (disorder)"
 },
 {
  "System": "http://snomed.info/sct",
  "Version": "2021-03",
  "Code": "25831001",
  "Display": "Tuberculosis of nasal septum (disorder)"
 },
 {
  "System": "http://snomed.info/sct",
  "Version": "2021-03",
  "Code": "267317007",
  "Display": "Tuberculosis in pregnancy (disorder)"
 },
 {
  "System": "http://snomed.info/sct",
  "Version": "2021-03",
  "Code": "26935004",
  "Display": "Tuberculosis of thyroid gland (disorder)"
 },
 {
  "System": "http://snomed.info/sct",
  "Version": "2021-03",
  "Code": "271423008",
  "Display": "Tuberculosis of skin and subcutaneous tissue (disorder)"
 },
 {
  "System": "http://snomed.info/sct",
  "Version": "2021-03",
  "Code": "281623008",
  "Display": "Genital tuberculosis (disorder)"
 },
 {
  "System": "http://snomed.info/sct",
  "Version": "2021-03",
  "Code": "28399005",
  "Display": "Tuberculosis of spleen (disorder)"
 },
 {
  "System": "http://snomed.info/sct",
  "Version": "2021-03",
  "Code": "29731002",
  "Display": "Tuberculous pneumothorax (disorder)"
 },
 {
  "System": "http://snomed.info/sct",
  "Version": "2021-03",
  "Code": "301836007",
  "Display": "Tuberculosis of colon (disorder)"
 },
 {
  "System": "http://snomed.info/sct",
  "Version": "2021-03",
  "Code": "302131003",
  "Display": "Tuberculosis of heart (disorder)"
 },
 {
  "System": "http://snomed.info/sct",
  "Version": "2021-03",
  "Code": "31112008",
  "Display": "Tuberculous meningoencephalitis (disorder)"
 },
 {
  "System": "http://snomed.info/sct",
  "Version": "2021-03",
  "Code": "314029000",
  "Display": "Tuberculous uveitis (disorder)"
 },
 {
  "System": "http://snomed.info/sct",
  "Version": "2021-03",
  "Code": "32268008",
  "Display": "Tuberculosis of bladder (disorder)"
 },
 {
  "System": "http://snomed.info/sct",
  "Version": "2021-03",
  "Code": "33893009",
  "Display": "Tuberculosis verrucosa cutis (disorder)"
 },
 {
  "System": "http://snomed.info/sct",
  "Version": "2021-03",
  "Code": "35585004",
  "Display": "Tuberculous endometritis (disorder)"
 },
 {
  "System": "http://snomed.info/sct",
  "Version": "2021-03",
  "Code": "35786001",
  "Display": "Tuberculoma of meninges (disorder)"
 },
 {
  "System": "http://snomed.info/sct",
  "Version": "2021-03",
  "Code": "35984006",
  "Display": "Tuberculosis of vertebral column (disorder)"
 },
 {
  "System": "http://snomed.info/sct",
  "Version": "2021-03",
  "Code": "37133005",
  "Display": "Tuberculous pyelitis (disorder)"
 },
 {
  "System": "http://snomed.info/sct",
  "Version": "2021-03",
  "Code": "37260006",
  "Display": "Congenital tuberculosis (disorder)"
 },
 {
  "System": "http://snomed.info/sct",
  "Version": "2021-03",
  "Code": "373043002",
  "Display": "Infection caused by Mycobacterium microti (disorder)"
 },
 {
  "System": "http://snomed.info/sct",
  "Version": "2021-03",
  "Code": "373085003",
  "Display": "Infection caused by Mycobacterium africanum (disorder)"
 },
 {
  "System": "http://snomed.info/sct",
  "Version": "2021-03",
  "Code": "373086002",
  "Display": "Infection caused by mycobacterium tuberculosis hominis (disorder)"
 },
 {
  "System": "http://snomed.info/sct",
  "Version": "2021-03",
  "Code": "373437006",
  "Display": "Infection caused by Mycobacterium bovis (disorder)"
 },
 {
  "System": "http://snomed.info/sct",
  "Version": "2021-03",
  "Code": "373576009",
  "Display": "Infection caused by Mycobacterium tuberculosis (disorder)"
 },
 {
  "System": "http://snomed.info/sct",
  "Version": "2021-03",
  "Code": "38115001",
  "Display": "Tuberculosis of spinal meninges (disorder)"
 },
 {
  "System": "http://snomed.info/sct",
  "Version": "2021-03",
  "Code": "38279006",
  "Display": "Tuberculosis of bone (disorder)"
 },
 {
  "System": "http://snomed.info/sct",
  "Version": "2021-03",
  "Code": "38420005",
  "Display": "Tuberculosis of large intestine (disorder)"
 },
 {
  "System": "http://snomed.info/sct",
  "Version": "2021-03",
  "Code": "39306006",
  "Display": "Tuberculosis of anus (disorder)"
 },
 {
  "System": "http://snomed.info/sct",
  "Version": "2021-03",
  "Code": "40258005",
  "Display": "Tuberculosis of testis (disorder)"
 },
 {
  "System": "http://snomed.info/sct",
  "Version": "2021-03",
  "Code": "402973006",
  "Display": "Bacillus Calmette-Guerin-induced lupus vulgaris (disorder)"
 },
 {
  "System": "http://snomed.info/sct",
  "Version": "2021-03",
  "Code": "402974000",
  "Display": "Bacillus Calmette-Guerin-induced scrofuloderma (disorder)"
 },
 {
  "System": "http://snomed.info/sct",
  "Version": "2021-03",
  "Code": "402975004",
  "Display": "Bacillus Calmette-Guerin-induced tuberculide (disorder)"
 },
 {
  "System": "http://snomed.info/sct",
  "Version": "2021-03",
  "Code": "413556004",
  "Display": "Antibiotic resistant tuberculosis (disorder)"
 },
 {
  "System": "http://snomed.info/sct",
  "Version": "2021-03",
  "Code": "413852006",
  "Display": "Ciprofloxacin resistant tuberculosis (disorder)"
 },
 {
  "System": "http://snomed.info/sct",
  "Version": "2021-03",
  "Code": "414146004",
  "Display": "Ethambutol resistant tuberculosis (disorder)"
 },
 {
  "System": "http://snomed.info/sct",
  "Version": "2021-03",
  "Code": "414149006",
  "Display": "Ethionamide resistant tuberculosis (disorder)"
 },
 {
  "System": "http://snomed.info/sct",
  "Version": "2021-03",
  "Code": "414546009",
  "Display": "Isoniazid resistant tuberculosis (disorder)"
 },
 {
  "System": "http://snomed.info/sct",
  "Version": "2021-03",
  "Code": "415222009",
  "Display": "Pyrazinamide resistant tuberculosis (disorder)"
 },
 {
  "System": "http://snomed.info/sct",
  "Version": "2021-03",
  "Code": "415345001",
  "Display": "Rifampicin resistant tuberculosis (disorder)"
 },
 {
  "System": "http://snomed.info/sct",
  "Version": "2021-03",
  "Code": "415622003",
  "Display": "Streptomycin resistant tuberculosis (disorder)"
 },
 {
  "System": "http://snomed.info/sct",
  "Version": "2021-03",
  "Code": "416265003",
  "Display": "Tuberculoma of brain (disorder)"
 },
 {
  "System": "http://snomed.info/sct",
  "Version": "2021-03",
  "Code": "416903004",
  "Display": "Tuberculoma of spinal cord (disorder)"
 },
 {
  "System": "http://snomed.info/sct",
  "Version": "2021-03",
  "Code": "421571007",
  "Display": "Tuberculosis associated with acquired immunodeficiency syndrome (disorder)"
 },
 {
  "System": "http://snomed.info/sct",
  "Version": "2021-03",
  "Code": "422481005",
  "Display": "Extreme drug resistant tuberculosis (disorder)"
 },
 {
  "System": "http://snomed.info/sct",
  "Version": "2021-03",
  "Code": "4225003",
  "Display": "Tuberculosis of nose (disorder)"
 },
 {
  "System": "http://snomed.info/sct",
  "Version": "2021-03",
  "Code": "423092005",
  "Display": "Multidrug resistant tuberculosis (disorder)"
 },
 {
  "System": "http://snomed.info/sct",
  "Version": "2021-03",
  "Code": "423709000",
  "Display": "Drug resistant tuberculosis (disorder)"
 },
 {
  "System": "http://snomed.info/sct",
  "Version": "2021-03",
  "Code": "423997002",
  "Display": "Tuberculosis"
 },
 {
  "System": "http://snomed.info/sct",
  "Version": "2021-03",
  "Code": "427099000",
  "Display": "Active tuberculosis (disorder)"
 },
 {
  "System": "http://snomed.info/sct",
  "Version": "2021-03",
  "Code": "428697002",
  "Display": "Inactive tuberculosis of lung (disorder)"
 },
 {
  "System": "http://snomed.info/sct",
  "Version": "2021-03",
  "Code": "428934008",
  "Display": "History of inactive tuberculosis (situation)"
 },
 {
  "System": "http://snomed.info/sct",
  "Version": "2021-03",
  "Code": "441770001",
  "Display": "Tuberculosis of external body orifice (disorder)"
 },
 {
  "System": "http://snomed.info/sct",
  "Version": "2021-03",
  "Code": "44182001",
  "Display": "Tuberculous necrosis of bone (disorder)"
 },
 {
  "System": "http://snomed.info/sct",
  "Version": "2021-03",
  "Code": "44323002",
  "Display": "Tuberculosis of kidney (disorder)"
 },
 {
  "System": "http://snomed.info/sct",
  "Version": "2021-03",
  "Code": "443378001",
  "Display": "Lady Windermere syndrome (disorder)"
 },
 {
  "System": "http://snomed.info/sct",
  "Version": "2021-03",
  "Code": "4445009",
  "Display": "Tuberculosis of genitourinary system (disorder)"
 },
 {
  "System": "http://snomed.info/sct",
  "Version": "2021-03",
  "Code": "44572005",
  "Display": "Tuberculous peritonitis (disorder)"
 },
 {
  "System": "http://snomed.info/sct",
  "Version": "2021-03",
  "Code": "446753005",
  "Display": "Tuberculosis of oropharynx (disorder)"
 },
 {
  "System": "http://snomed.info/sct",
  "Version": "2021-03",
  "Code": "446946005",
  "Display": "Reinfection pulmonary tuberculosis (disorder)"
 },
 {
  "System": "http://snomed.info/sct",
  "Version": "2021-03",
  "Code": "446986002",
  "Display": "Tuberculous pleural effusion (disorder)"
 },
 {
  "System": "http://snomed.info/sct",
  "Version": "2021-03",
  "Code": "447006007",
  "Display": "Relapse pulmonary tuberculosis (disorder)"
 },
 {
  "System": "http://snomed.info/sct",
  "Version": "2021-03",
  "Code": "447012002",
  "Display": "Tuberculosis of spinal cord (disorder)"
 },
 {
  "System": "http://snomed.info/sct",
  "Version": "2021-03",
  "Code": "447253004",
  "Display": "Tuberculous arachnoiditis (disorder)"
 },
 {
  "System": "http://snomed.info/sct",
  "Version": "2021-03",
  "Code": "447330002",
  "Display": "Tuberculosis of abdomen (disorder)"
 },
 {
  "System": "http://snomed.info/sct",
  "Version": "2021-03",
  "Code": "447371008",
  "Display": "Tuberculosis of ileum (disorder)"
 },
 {
  "System": "http://snomed.info/sct",
  "Version": "2021-03",
  "Code": "449925002",
  "Display": "Tuberculosis of bone of upper limb (disorder)"
 },
 {
  "System": "http://snomed.info/sct",
  "Version": "2021-03",
  "Code": "4501007",
  "Display": "Tuberculous ascites (disorder)"
 },
 {
  "System": "http://snomed.info/sct",
  "Version": "2021-03",
  "Code": "460440005",
  "Display": "Pericarditis with pericardial effusion caused by Mycobacterium tuberculosis complex (disorder)"
 },
 {
  "System": "http://snomed.info/sct",
  "Version": "2021-03",
  "Code": "460464006",
  "Display": "Constrictive pericarditis caused by Mycobacterium tuberculosis complex (disorder)"
 },
 {
  "System": "http://snomed.info/sct",
  "Version": "2021-03",
  "Code": "47292005",
  "Display": "Tuberculosis of myocardium (disorder)"
 },
 {
  "System": "http://snomed.info/sct",
  "Version": "2021-03",
  "Code": "473114006",
  "Display": "History of active tuberculosis (situation)"
 },
 {
  "System": "http://snomed.info/sct",
  "Version": "2021-03",
  "Code": "473426009",
  "Display": "Primary tuberculous complex confirmed by culture (disorder)"
 },
 {
  "System": "http://snomed.info/sct",
  "Version": "2021-03",
  "Code": "473427000",
  "Display": "Primary tuberculous complex confirmed histologically (disorder)"
 },
 {
  "System": "http://snomed.info/sct",
  "Version": "2021-03",
  "Code": "473428005",
  "Display": "Primary tuberculous complex confirmed by microscopic examination (disorder)"
 },
 {
  "System": "http://snomed.info/sct",
  "Version": "2021-03",
  "Code": "473429002",
  "Display": "Tuberculoma of spinal cord confirmed (disorder)"
 },
 {
  "System": "http://snomed.info/sct",
  "Version": "2021-03",
  "Code": "473430007",
  "Display": "Primary tuberculous complex confirmed (disorder)"
 },
 {
  "System": "http://snomed.info/sct",
  "Version": "2021-03",
  "Code": "473431006",
  "Display": "Primary tuberculous complex with bacteriological or histological examination results unknown (disorder)"
 },
 {
  "System": "http://snomed.info/sct",
  "Version": "2021-03",
  "Code": "47604008",
  "Display": "Miliary tuberculosis (disorder)"
 },
 {
  "System": "http://snomed.info/sct",
  "Version": "2021-03",
  "Code": "48225000",
  "Display": "Tuberculous disseminated chorioretinitis (disorder)"
 },
 {
  "System": "http://snomed.info/sct",
  "Version": "2021-03",
  "Code": "49107007",
  "Display": "Tuberculosis of eye (disorder)"
 },
 {
  "System": "http://snomed.info/sct",
  "Version": "2021-03",
  "Code": "49558004",
  "Display": "Tuberculous salpingitis (disorder)"
 },
 {
  "System": "http://snomed.info/sct",
  "Version": "2021-03",
  "Code": "49807009",
  "Display": "Tuberculous dactylitis (disorder)"
 },
 {
  "System": "http://snomed.info/sct",
  "Version": "2021-03",
  "Code": "51014003",
  "Display": "Reinfection tuberculosis (disorder)"
 },
 {
  "System": "http://snomed.info/sct",
  "Version": "2021-03",
  "Code": "52721006",
  "Display": "Tuberculosis of nasal sinus (disorder)"
 },
 {
  "System": "http://snomed.info/sct",
  "Version": "2021-03",
  "Code": "52987001",
  "Display": "Tuberculosis of endocardium (disorder)"
 },
 {
  "System": "http://snomed.info/sct",
  "Version": "2021-03",
  "Code": "54084005",
  "Display": "Cervical tuberculous lymphadenitis (disorder)"
 },
 {
  "System": "http://snomed.info/sct",
  "Version": "2021-03",
  "Code": "55419007",
  "Display": "Tuberculosis of glottis (disorder)"
 },
 {
  "System": "http://snomed.info/sct",
  "Version": "2021-03",
  "Code": "56498009",
  "Display": "Tuberculosis of nasopharynx (disorder)"
 },
 {
  "System": "http://snomed.info/sct",
  "Version": "2021-03",
  "Code": "56717001",
  "Display": "Tuberculosis (disorder)"
 },
 {
  "System": "http://snomed.info/sct",
  "Version": "2021-03",
  "Code": "58374007",
  "Display": "Acute diffuse tuberculosis (disorder)"
 },
 {
  "System": "http://snomed.info/sct",
  "Version": "2021-03",
  "Code": "58437007",
  "Display": "Tuberculosis of meninges (disorder)"
 },
 {
  "System": "http://snomed.info/sct",
  "Version": "2021-03",
  "Code": "58764007",
  "Display": "Tuberculous osteomyelitis (disorder)"
 },
 {
  "System": "http://snomed.info/sct",
  "Version": "2021-03",
  "Code": "60136008",
  "Display": "Tuberculosis of intestines (disorder)"
 },
 {
  "System": "http://snomed.info/sct",
  "Version": "2021-03",
  "Code": "62494007",
  "Display": "Chronic miliary tuberculosis (disorder)"
 },
 {
  "System": "http://snomed.info/sct",
  "Version": "2021-03",
  "Code": "62819009",
  "Display": "Tuberculous cervicitis (disorder)"
 },
 {
  "System": "http://snomed.info/sct",
  "Version": "2021-03",
  "Code": "63309002",
  "Display": "Primary tuberculosis (disorder)"
 },
 {
  "System": "http://snomed.info/sct",
  "Version": "2021-03",
  "Code": "63808004",
  "Display": "Tuberculous chancre (disorder)"
 },
 {
  "System": "http://snomed.info/sct",
  "Version": "2021-03",
  "Code": "66986005",
  "Display": "Tuberculosis of skin (disorder)"
 },
 {
  "System": "http://snomed.info/sct",
  "Version": "2021-03",
  "Code": "67256000",
  "Display": "Tuberculosis of pericardium (disorder)"
 },
 {
  "System": "http://snomed.info/sct",
  "Version": "2021-03",
  "Code": "700272008",
  "Display": "Tuberculosis of respiratory system (disorder)"
 },
 {
  "System": "http://snomed.info/sct",
  "Version": "2021-03",
  "Code": "700273003",
  "Display": "Isolated tracheobronchial tuberculosis (disorder)"
 },
 {
  "System": "http://snomed.info/sct",
  "Version": "2021-03",
  "Code": "70341005",
  "Display": "Tuberculous laryngitis (disorder)"
 },
 {
  "System": "http://snomed.info/sct",
  "Version": "2021-03",
  "Code": "707149004",
  "Display": "Mycobacterial lymphadenitis (disorder)"
 },
 {
  "System": "http://snomed.info/sct",
  "Version": "2021-03",
  "Code": "710106005",
  "Display": "Extensively drug resistant tuberculosis (disorder)"
 },
 {
  "System": "http://snomed.info/sct",
  "Version": "2021-03",
  "Code": "71375000",
  "Display": "Tuberculosis of mastoid process (disorder)"
 },
 {
  "System": "http://snomed.info/sct",
  "Version": "2021-03",
  "Code": "714394004",
  "Display": "Lupus vulgaris of nose (disorder)"
 },
 {
  "System": "http://snomed.info/sct",
  "Version": "2021-03",
  "Code": "717697005",
  "Display": "Tuberculous ulceration of vulva (disorder)"
 },
 {
  "System": "http://snomed.info/sct",
  "Version": "2021-03",
  "Code": "71943007",
  "Display": "Chronic granulomatous tuberculosis (disorder)"
 },
 {
  "System": "http://snomed.info/sct",
  "Version": "2021-03",
  "Code": "721732001",
  "Display": "Infection of musculoskeletal system caused by Mycobacterium tuberculosis (disorder)"
 },
 {
  "System": "http://snomed.info/sct",
  "Version": "2021-03",
  "Code": "724541008",
  "Display": "Acute miliary tuberculosis of single site (disorder)"
 },
 {
  "System": "http://snomed.info/sct",
  "Version": "2021-03",
  "Code": "72807002",
  "Display": "Tuberculous polyserositis (disorder)"
 },
 {
  "System": "http://snomed.info/sct",
  "Version": "2021-03",
  "Code": "733835007",
  "Display": "Extrapulmonary tuberculosis co-occurrent with human immunodeficiency virus infection (disorder)"
 },
 {
  "System": "http://snomed.info/sct",
  "Version": "2021-03",
  "Code": "735517008",
  "Display": "Myositis caused by Mycobacterium tuberculosis (disorder)"
 },
 {
  "System": "http://snomed.info/sct",
  "Version": "2021-03",
  "Code": "735518003",
  "Display": "Infection of digestive system caused by Mycobacterium tuberculosis (disorder)"
 },
 {
  "System": "http://snomed.info/sct",
  "Version": "2021-03",
  "Code": "735519006",
  "Display": "Infection of endocrine gland caused by Mycobacterium tuberculosis (disorder)"
 },
 {
  "System": "http://snomed.info/sct",
  "Version": "2021-03",
  "Code": "735521001",
  "Display": "Human immunodeficiency virus World Health Organization 2007 stage 1 co-occurrent with tuberculosis (disorder)"
 },
 {
  "System": "http://snomed.info/sct",
  "Version": "2021-03",
  "Code": "735523003",
  "Display": "Human immunodeficiency virus World Health Organization 2007 stage 2 co-occurrent with tuberculosis (disorder)"
 },
 {
  "System": "http://snomed.info/sct",
  "Version": "2021-03",
  "Code": "735525005",
  "Display": "Human immunodeficiency virus World Health Organization 2007 stage 3 co-occurrent with tuberculosis (disorder)"
 },
 {
  "System": "http://snomed.info/sct",
  "Version": "2021-03",
  "Code": "735527002",
  "Display": "Human immunodeficiency virus World Health Organization 2007 stage 4 co-occurrent with tuberculosis (disorder)"
 },
 {
  "System": "http://snomed.info/sct",
  "Version": "2021-03",
  "Code": "74181004",
  "Display": "Tuberculosis of female genital organs (disorder)"
 },
 {
  "System": "http://snomed.info/sct",
  "Version": "2021-03",
  "Code": "74387008",
  "Display": "Tuberculosis of hilar lymph nodes (disorder)"
 },
 {
  "System": "http://snomed.info/sct",
  "Version": "2021-03",
  "Code": "7444001",
  "Display": "Tuberculosis of rectum (disorder)"
 },
 {
  "System": "http://snomed.info/sct",
  "Version": "2021-03",
  "Code": "74610006",
  "Display": "Tuberculous erythema nodosum (disorder)"
 },
 {
  "System": "http://snomed.info/sct",
  "Version": "2021-03",
  "Code": "77038006",
  "Display": "Tuberculosis of peripheral lymph nodes (disorder)"
 },
 {
  "System": "http://snomed.info/sct",
  "Version": "2021-03",
  "Code": "770674007",
  "Display": "Tubercular lesion of lung (disorder)"
 },
 {
  "System": "http://snomed.info/sct",
  "Version": "2021-03",
  "Code": "78436002",
  "Display": "Tuberculosis of intrathoracic lymph nodes (disorder)"
 },
 {
  "System": "http://snomed.info/sct",
  "Version": "2021-03",
  "Code": "788960009",
  "Display": "Infection of placenta caused by Mycobacterium tuberculosis complex (disorder)"
 },
 {
  "System": "http://snomed.info/sct",
  "Version": "2021-03",
  "Code": "789056000",
  "Display": "Tuberculosis of inner ear (disorder)"
 },
 {
  "System": "http://snomed.info/sct",
  "Version": "2021-03",
  "Code": "789057009",
  "Display": "Tuberculosis of middle ear (disorder)"
 },
 {
  "System": "http://snomed.info/sct",
  "Version": "2021-03",
  "Code": "79158003",
  "Display": "Tuberculous interstitial keratitis (disorder)"
 },
 {
  "System": "http://snomed.info/sct",
  "Version": "2021-03",
  "Code": "80003002",
  "Display": "Tuberculous pneumonia (disorder)"
 },
 {
  "System": "http://snomed.info/sct",
  "Version": "2021-03",
  "Code": "80010008",
  "Display": "Isolated bronchial tuberculosis (disorder)"
 },
 {
  "System": "http://snomed.info/sct",
  "Version": "2021-03",
  "Code": "80602006",
  "Display": "Nodular tuberculosis of lung (disorder)"
 },
 {
  "System": "http://snomed.info/sct",
  "Version": "2021-03",
  "Code": "81133003",
  "Display": "Tuberculosis of bones of lower extremity (disorder)"
 },
 {
  "System": "http://snomed.info/sct",
  "Version": "2021-03",
  "Code": "81359005",
  "Display": "Tuberculosis of ureter (disorder)"
 },
 {
  "System": "http://snomed.info/sct",
  "Version": "2021-03",
  "Code": "81554001",
  "Display": "Tuberculosis of lung with involvement of bronchus (disorder)"
 },
 {
  "System": "http://snomed.info/sct",
  "Version": "2021-03",
  "Code": "82495004",
  "Display": "Tuberculosis of mediastinal lymph nodes (disorder)"
 },
 {
  "System": "http://snomed.info/sct",
  "Version": "2021-03",
  "Code": "8250007",
  "Display": "Tuberculosis of subcutaneous cellular tissue (disorder)"
 },
 {
  "System": "http://snomed.info/sct",
  "Version": "2021-03",
  "Code": "82796002",
  "Display": "Scrofuloderma (disorder)"
 },
 {
  "System": "http://snomed.info/sct",
  "Version": "2021-03",
  "Code": "83652003",
  "Display": "Tuberculosis of epididymis (disorder)"
 },
 {
  "System": "http://snomed.info/sct",
  "Version": "2021-03",
  "Code": "83784000",
  "Display": "Tuberculosis of mediastinum (disorder)"
 },
 {
  "System": "http://snomed.info/sct",
  "Version": "2021-03",
  "Code": "840446000",
  "Display": "Dacryoadenitis caused by Mycobacterium tuberculosis (disorder)"
 },
 {
  "System": "http://snomed.info/sct",
  "Version": "2021-03",
  "Code": "84194006",
  "Display": "Tuberculous oophoritis (disorder)"
 },
 {
  "System": "http://snomed.info/sct",
  "Version": "2021-03",
  "Code": "84288007",
  "Display": "Tuberculous episcleritis (disorder)"
 },
 {
  "System": "http://snomed.info/sct",
  "Version": "2021-03",
  "Code": "85692003",
  "Display": "Tuberculosis of tracheobronchial lymph nodes (disorder)"
 },
 {
  "System": "http://snomed.info/sct",
  "Version": "2021-03",
  "Code": "85940005",
  "Display": "Tuberculous otitis media (disorder)"
 },
 {
  "System": "http://snomed.info/sct",
  "Version": "2021-03",
  "Code": "860803004",
  "Display": "Hydrocephalus due to tuberculosis of brain (disorder)"
 },
 {
  "System": "http://snomed.info/sct",
  "Version": "2021-03",
  "Code": "866083008",
  "Display": "Infection of eyelid caused by Mycobacterium tuberculosis (disorder)"
 },
 {
  "System": "http://snomed.info/sct",
  "Version": "2021-03",
  "Code": "870333003",
  "Display": "Panuveitis caused by Mycobacterium tuberculosis (disorder)"
 },
 {
  "System": "http://snomed.info/sct",
  "Version": "2021-03",
  "Code": "8832006",
  "Display": "Tuberculosis orificialis of anus (disorder)"
 },
 {
  "System": "http://snomed.info/sct",
  "Version": "2021-03",
  "Code": "88356006",
  "Display": "Primary tuberculous complex (disorder)"
 },
 {
  "System": "http://snomed.info/sct",
  "Version": "2021-03",
  "Code": "90117007",
  "Display": "Tuberculous fibrosis of lung (disorder)"
 },
 {
  "System": "http://snomed.info/sct",
  "Version": "2021-03",
  "Code": "90302003",
  "Display": "Tuberculosis of cerebral meninges (disorder)"
 },
 {
  "System": "http://snomed.info/sct",
  "Version": "2021-03",
  "Code": "91483004",
  "Display": "Tuberculous encephalitis (disorder)"
 },
 {
  "System": "http://hl7.org/fhir/sid/icd-10-cm",
  "Version": "2022",
  "Code": "A15.0",
  "Display": "Tuberculosis of lung"
 },
 {
  "System": "http://hl7.org/fhir/sid/icd-10-cm",
  "Version": "2022",
  "Code": "A15.4",
  "Display": "Tuberculosis of intrathoracic lymph nodes"
 },
 {
  "System": "http://hl7.org/fhir/sid/icd-10-cm",
  "Version": "2022",
  "Code": "A15.5",
  "Display": "Tuberculosis of larynx"
 },
 {
  "System": "http://hl7.org/fhir/sid/icd-10-cm",
  "Version": "2022",
  "Code": "A15.6",
  "Display": "Tuberculous pleurisy"
 },
 {
  "System": "http://hl7.org/fhir/sid/icd-10-cm",
  "Version": "2022",
  "Code": "A15.7",
  "Display": "Primary respiratory tuberculosis"
 },
 {
  "System": "http://hl7.org/fhir/sid/icd-10-cm",
  "Version": "2022",
  "Code": "A15.8",
  "Display": "Other respiratory tuberculosis"
 },
 {
  "System": "http://hl7.org/fhir/sid/icd-10-cm",
  "Version": "2022",
  "Code": "A15.9",
  "Display": "Respiratory tuberculosis unspecified"
 },
 {
  "System": "http://hl7.org/fhir/sid/icd-10-cm",
  "Version": "2022",
  "Code": "A17.0",
  "Display": "Tuberculous meningitis"
 },
 {
  "System": "http://hl7.org/fhir/sid/icd-10-cm",
  "Version": "2022",
  "Code": "A17.1",
  "Display": "Meningeal tuberculoma"
 },
 {
  "System": "http://hl7.org/fhir/sid/icd-10-cm",
  "Version": "2022",
  "Code": "A17.81",
  "Display": "Tuberculoma of brain and spinal cord"
 },
 {
  "System": "http://hl7.org/fhir/sid/icd-10-cm",
  "Version": "2022",
  "Code": "A17.82",
  "Display": "Tuberculous meningoencephalitis"
 },
 {
  "System": "http://hl7.org/fhir/sid/icd-10-cm",
  "Version": "2022",
  "Code": "A17.83",
  "Display": "Tuberculous neuritis"
 },
 {
  "System": "http://hl7.org/fhir/sid/icd-10-cm",
  "Version": "2022",
  "Code": "A17.89",
  "Display": "Other tuberculosis of nervous system"
 },
 {
  "System": "http://hl7.org/fhir/sid/icd-10-cm",
  "Version": "2022",
  "Code": "A17.9",
  "Display": "Tuberculosis of nervous system"
 },
 {
  "System": "http://hl7.org/fhir/sid/icd-10-cm",
  "Version": "2022",
  "Code": "A18.01",
  "Display": "Tuberculosis of spine"
 },
 {
  "System": "http://hl7.org/fhir/sid/icd-10-cm",
  "Version": "2022",
  "Code": "A18.02",
  "Display": "Tuberculous arthritis of other joints"
 },
 {
  "System": "http://hl7.org/fhir/sid/icd-10-cm",
  "Version": "2022",
  "Code": "A18.03",
  "Display": "Tuberculosis of other bones"
 },
 {
  "System": "http://hl7.org/fhir/sid/icd-10-cm",
  "Version": "2022",
  "Code": "A18.09",
  "Display": "Other musculoskeletal tuberculosis"
 },
 {
  "System": "http://hl7.org/fhir/sid/icd-10-cm",
  "Version": "2022",
  "Code": "A18.1",
  "Display": "Tuberculosis of genitourinary system"
 },
 {
  "System": "http://hl7.org/fhir/sid/icd-10-cm",
  "Version": "2022",
  "Code": "A18.10",
  "Display": "Tuberculosis of genitourinary system"
 },
 {
  "System": "http://hl7.org/fhir/sid/icd-10-cm",
  "Version": "2022",
  "Code": "A18.11",
  "Display": "Tuberculosis of kidney and ureter"
 },
 {
  "System": "http://hl7.org/fhir/sid/icd-10-cm",
  "Version": "2022",
  "Code": "A18.12",
  "Display": "Tuberculosis of bladder"
 },
 {
  "System": "http://hl7.org/fhir/sid/icd-10-cm",
  "Version": "2022",
  "Code": "A18.13",
  "Display": "Tuberculosis of other urinary organs"
 },
 {
  "System": "http://hl7.org/fhir/sid/icd-10-cm",
  "Version": "2022",
  "Code": "A18.14",
  "Display": "Tuberculosis of prostate"
 },
 {
  "System": "http://hl7.org/fhir/sid/icd-10-cm",
  "Version": "2022",
  "Code": "A18.15",
  "Display": "Tuberculosis of other male genital organs"
 },
 {
  "System": "http://hl7.org/fhir/sid/icd-10-cm",
  "Version": "2022",
  "Code": "A18.16",
  "Display": "Tuberculosis of cervix"
 },
 {
  "System": "http://hl7.org/fhir/sid/icd-10-cm",
  "Version": "2022",
  "Code": "A18.17",
  "Display": "Tuberculous female pelvic inflammatory disease"
 },
 {
  "System": "http://hl7.org/fhir/sid/icd-10-cm",
  "Version": "2022",
  "Code": "A18.18",
  "Display": "Tuberculosis of other female genital organs"
 },
 {
  "System": "http://hl7.org/fhir/sid/icd-10-cm",
  "Version": "2022",
  "Code": "A18.2",
  "Display": "Tuberculous peripheral lymphadenopathy"
 },
 {
  "System": "http://hl7.org/fhir/sid/icd-10-cm",
  "Version": "2022",
  "Code": "A18.3",
  "Display": "Tuberculosis of intestines"
 },
 {
  "System": "http://hl7.org/fhir/sid/icd-10-cm",
  "Version": "2022",
  "Code": "A18.31",
  "Display": "Tuberculous peritonitis"
 },
 {
  "System": "http://hl7.org/fhir/sid/icd-10-cm",
  "Version": "2022",
  "Code": "A18.32",
  "Display": "Tuberculous enteritis"
 },
 {
  "System": "http://hl7.org/fhir/sid/icd-10-cm",
  "Version": "2022",
  "Code": "A18.39",
  "Display": "Retroperitoneal tuberculosis"
 },
 {
  "System": "http://hl7.org/fhir/sid/icd-10-cm",
  "Version": "2022",
  "Code": "A18.4",
  "Display": "Tuberculosis of skin and subcutaneous tissue"
 },
 {
  "System": "http://hl7.org/fhir/sid/icd-10-cm",
  "Version": "2022",
  "Code": "A18.5",
  "Display": "Tuberculosis of eye"
 },
 {
  "System": "http://hl7.org/fhir/sid/icd-10-cm",
  "Version": "2022",
  "Code": "A18.50",
  "Display": "Tuberculosis of eye"
 },
 {
  "System": "http://hl7.org/fhir/sid/icd-10-cm",
  "Version": "2022",
  "Code": "A18.51",
  "Display": "Tuberculous episcleritis"
 },
 {
  "System": "http://hl7.org/fhir/sid/icd-10-cm",
  "Version": "2022",
  "Code": "A18.52",
  "Display": "Tuberculous keratitis"
 },
 {
  "System": "http://hl7.org/fhir/sid/icd-10-cm",
  "Version": "2022",
  "Code": "A18.53",
  "Display": "Tuberculous chorioretinitis"
 },
 {
  "System": "http://hl7.org/fhir/sid/icd-10-cm",
  "Version": "2022",
  "Code": "A18.54",
  "Display": "Tuberculous iridocyclitis"
 },
 {
  "System": "http://hl7.org/fhir/sid/icd-10-cm",
  "Version": "2022",
  "Code": "A18.59",
  "Display": "Other tuberculosis of eye"
 },
 {
  "System": "http://hl7.org/fhir/sid/icd-10-cm",
  "Version": "2022",
  "Code": "A18.6",
  "Display": "Tuberculosis of (inner) (middle) ear"
 },
 {
  "System": "http://hl7.org/fhir/sid/icd-10-cm",
  "Version": "2022",
  "Code": "A18.7",
  "Display": "Tuberculosis of adrenal glands"
 },
 {
  "System": "http://hl7.org/fhir/sid/icd-10-cm",
  "Version": "2022",
  "Code": "A18.8",
  "Display": "Tuberculosis of other specified organs"
 },
 {
  "System": "http://hl7.org/fhir/sid/icd-10-cm",
  "Version": "2022",
  "Code": "A18.81",
  "Display": "Tuberculosis of thyroid gland"
 },
 {
  "System": "http://hl7.org/fhir/sid/icd-10-cm",
  "Version": "2022",
  "Code": "A18.82",
  "Display": "Tuberculosis of other endocrine glands"
 },
 {
  "System": "http://hl7.org/fhir/sid/icd-10-cm",
  "Version": "2022",
  "Code": "A18.83",
  "Display": "Tuberculosis of digestive tract organs"
 },
 {
  "System": "http://hl7.org/fhir/sid/icd-10-cm",
  "Version": "2022",
  "Code": "A18.84",
  "Display": "Tuberculosis of heart"
 },
 {
  "System": "http://hl7.org/fhir/sid/icd-10-cm",
  "Version": "2022",
  "Code": "A18.85",
  "Display": "Tuberculosis of spleen"
 },
 {
  "System": "http://hl7.org/fhir/sid/icd-10-cm",
  "Version": "2022",
  "Code": "A18.89",
  "Display": "Tuberculosis of other sites"
 },
 {
  "System": "http://hl7.org/fhir/sid/icd-10-cm",
  "Version": "2022",
  "Code": "A19.0",
  "Display": "Acute miliary tuberculosis of a single specified site"
 },
 {
  "System": "http://hl7.org/fhir/sid/icd-10-cm",
  "Version": "2022",
  "Code": "A19.1",
  "Display": "Acute miliary tuberculosis of multiple sites"
 },
 {
  "System": "http://hl7.org/fhir/sid/icd-10-cm",
  "Version": "2022",
  "Code": "A19.2",
  "Display": "Acute miliary tuberculosis"
 },
 {
  "System": "http://hl7.org/fhir/sid/icd-10-cm",
  "Version": "2022",
  "Code": "A19.8",
  "Display": "Other miliary tuberculosis"
 },
 {
  "System": "http://hl7.org/fhir/sid/icd-10-cm",
  "Version": "2022",
  "Code": "A19.9",
  "Display": "Miliary tuberculosis"
 },
 {
  "System": "http://hl7.org/fhir/sid/icd-10-cm",
  "Version": "2022",
  "Code": "B90.0",
  "Display": "Sequelae of central nervous system tuberculosis"
 },
 {
  "System": "http://hl7.org/fhir/sid/icd-10-cm",
  "Version": "2022",
  "Code": "B90.1",
  "Display": "Sequelae of genitourinary tuberculosis"
 },
 {
  "System": "http://hl7.org/fhir/sid/icd-10-cm",
  "Version": "2022",
  "Code": "B90.2",
  "Display": "Sequelae of tuberculosis of bones and joints"
 },
 {
  "System": "http://hl7.org/fhir/sid/icd-10-cm",
  "Version": "2022",
  "Code": "B90.8",
  "Display": "Sequelae of tuberculosis of other organs"
 },
 {
  "System": "http://hl7.org/fhir/sid/icd-10-cm",
  "Version": "2022",
  "Code": "B90.9",
  "Display": "Sequelae of respiratory and unspecified tuberculosis"
 },
 {
  "System": "http://hl7.org/fhir/sid/icd-10-cm",
  "Version": "2022",
  "Code": "J65",
  "Display": "Pneumoconiosis associated with tuberculosis"
 },
 {
  "System": "http://hl7.org/fhir/sid/icd-10-cm",
  "Version": "2022",
  "Code": "Z86.11",
  "Display": "Personal history of tuberculosis"
 }
]